src/inst_mem.v

// Date: May 2nd, 2025: 
// Author: Evan Wu 

/* Instruction Module */
// Stores and fetches the program 18-bit instructions to be executed by the microprocessor. 
// Implemented in Von Neumann architecture, 
// Instruction are addressed by the lower 13 bits of the address space.
// Instruction memory occupies addresses 0x0000 to 0x1FFF (13-bit address space). 
// Data memory occupies addresses 0x2000 to 0x3FFF (13-bit address space). 

// Future improvements: 

module inst_mem #(
    parameter INSTRUCTION_MEM_SIZE = 8192,
    parameter INSTRUCTION_WIDTH    = 18,
    parameter INSTRUCTION_ADDR_WIDTH = $clog2(INSTRUCTION_MEM_SIZE)+1,
    parameter MEM_BASE_ADDR = 14'h2000 // Programs are loaded 0x2000
) (
    input i_clk,
    input [INSTRUCTION_ADDR_WIDTH-1:0] i_address,
    output reg [INSTRUCTION_WIDTH-1:0] instruction
);
    
    // Defines Instruction 8kb memory array 
    reg [INSTRUCTION_WIDTH-1:0] memory [0:INSTRUCTION_MEM_SIZE-1]; 

    // Fetches an instruction from memory every clock cycle
    always @(posedge i_clk) 
        begin
            if (i_address >= MEM_BASE_ADDR) begin
                instruction <= memory[i_address-MEM_BASE_ADDR];
            end
            else if (i_address <= MEM_BASE_ADDR) begin
                instruction <= {INSTRUCTION_WIDTH{1'b0}}; // NOP or invalid
            end
        end
endmodule

testbench/inst_mem_tb.v


`timescale 1ns/ 1ps
`include "../src/inst_mem.v"

module inst_mem_tb;

    // Parameters
    localparam INSTRUCTION_MEM_SIZE    = 8192;
    localparam INSTRUCTION_WIDTH       = 18;
    localparam INSTRUCTION_ADDR_WIDTH  = $clog2(INSTRUCTION_MEM_SIZE)+1;
    parameter c_CLOCK_PERIOD_NS        = 100;

    // Inputs
    reg r_clk = 0;
    reg [INSTRUCTION_ADDR_WIDTH-1:0] i_address;

    // Output
    wire [INSTRUCTION_WIDTH-1:0] o_instruction;

    // Instantiate the Instruction Memory
    inst_mem #(
        .INSTRUCTION_MEM_SIZE(INSTRUCTION_MEM_SIZE),
        .INSTRUCTION_WIDTH(INSTRUCTION_WIDTH)
    ) uut (
        .i_clk(r_clk),
        .i_address(i_address),
        .instruction(o_instruction)
    );

    // Clock generation
    always
        #(c_CLOCK_PERIOD_NS/2) r_clk <= !r_clk;


    always @(posedge r_clk) begin
        $display("Time: %0t | Addr: %0d | Instruction: %0h", $time, i_address, o_instruction);
    end


    // Test data
    initial begin
        // Initialize signals
        r_clk = 0;
        i_address = 14'h2000;

        // Preload memory (optional: create `program.hex` file with 18-bit hex values)
        $readmemh("program.hex", uut.memory);

        // Wait and then test a few addresses        
        @(posedge r_clk)
        i_address <= 14'h2000;
        @(posedge r_clk)
        i_address <= 14'h2001;
        @(posedge r_clk)
        i_address <= 14'h2002;
        @(posedge r_clk)
        i_address <= 14'h2003;
        @(posedge r_clk)
        i_address <= 14'h2004;
        @(posedge r_clk)
        i_address <= 14'h2005;
        @(posedge r_clk)
        i_address <= 14'h2006;
        @(posedge r_clk)
        i_address <= 14'h2007; 
        @(posedge r_clk)
        i_address <= 14'h2008;
        @(posedge r_clk)
        i_address <= 14'h2009;
        @(posedge r_clk)
        $finish;
    end
    
    initial
    begin
        // Required to dump signals to EPWave
        $dumpfile("dump.vcd");
        $dumpvars(0);
    end
endmodule

testbench/dump.vcd
$date
	Mon May 05 21:31:20 2025
$end
$version
	Icarus Verilog
$end
$timescale
	1ps
$end
$scope module inst_mem_tb $end
$var wire 18 ! o_instruction [17:0] $end
$var reg 14 " i_address [13:0] $end
$var reg 1 # r_clk $end
$scope module uut $end
$var wire 14 $ i_address [13:0] $end
$var wire 1 % i_clk $end
$var reg 18 & instruction [17:0] $end
$upscope $end
$upscope $end
$enddefinitions $end
#0
$dumpvars
bx &
0%
b10000000000000 $
0#
b10000000000000 "
bx !
$end
#50000
b1 &
b1 !
1#
1%
#100000
0#
0%
#150000
b10000000000001 "
b10000000000001 $
1#
1%
#200000
0#
0%
#250000
b10010001101000101 &
b10010001101000101 !
b10000000000010 "
b10000000000010 $
1#
1%
#300000
0#
0%
#350000
b10000000000011 "
b10000000000011 $
b101010101010101010 &
b101010101010101010 !
1#
1%
#400000
0#
0%
#450000
b111111001111110011 &
b111111001111110011 !
b10000000000100 "
b10000000000100 $
1#
1%
#500000
0#
0%
#550000
b10000000000101 "
b10000000000101 $
b1100000011000000 &
b1100000011000000 !
1#
1%
#600000
0#
0%
#650000
b11101000111010001 &
b11101000111010001 !
b10000000000110 "
b10000000000110 $
1#
1%
#700000
0#
0%
#750000
b10000000000111 "
b10000000000111 $
b11111111111111111 &
b11111111111111111 !
1#
1%
#800000
0#
0%
#850000
b101111111111111111 &
b101111111111111111 !
b10000000001000 "
b10000000001000 $
1#
1%
#900000
0#
0%
#950000
b10000000001001 "
b10000000001001 $
b111111111011101010 &
b111111111011101010 !
1#
1%
#1000000
0#
0%
#1050000
bx &
bx !
1#
1%
