src/reg_file.v

// Date: May 3rd, 2025: 
// Author: Evan Wu 

/* 4x36 Register File */
// Inputs: 
// - i_clk: clock input
// - i_rst: reset input 
// - i_rs1: source register 1
// - i_rs2: source register 2
// - i_rd:  destination register 
// - i_w data: write data 
// - i_wen: write enable. data can only be written to register if signal is logic high.

// Outputs: 
// - o_rs1_data: source register 1 data
// - o_rs2_data: source register 2 data 

module reg_file #(
    parameter NUM_REGS = 4, 
    parameter DATA_WIDTH = 36, 
    parameter ADDRESS_WIDTH = $clog2(NUM_REGS)
) (
    input i_clk,
    input i_rst, 
    input [ADDRESS_WIDTH-1:0] i_rs1,
    input [ADDRESS_WIDTH-1:0] i_rs2, 
    input [ADDRESS_WIDTH-1:0] i_rd, 
    input [DATA_WIDTH-1:0]    i_wdata, 
    input i_wen,

    output reg [DATA_WIDTH-1:0] o_rs1_data,
    output reg [DATA_WIDTH-1:0] o_rs2_data
);
    

// Declare array of 4 general purpose registers
reg [DATA_WIDTH-1:0] r_regs [0:NUM_REGS-1];

// Asynchronous Read
always @(*)
    begin
        o_rs1_data <= r_regs[i_rs1];
        o_rs2_data <= r_regs[i_rs2];
    end


integer i = 0; 
// Synchronous Write
always @(posedge i_clk) 
    begin
        if (i_rst) // Reset all registers to 0
             begin
                for (i = 0; i < NUM_REGS; i = i+1)
                    begin
                        r_regs[i] <= 0;
                    end
            end
        else if (i_wen) // if write is enabled, write data to destination register.
            begin
                r_regs[i_rd] <= i_wdata; 
            end
    end
endmodule

testbench/reg_file_tb.v



`timescale 1ns/ 1ps
`include "../src/reg_file.v"

module reg_file_tb(); 

    localparam c_CLOCK_PERIOD_NS = 100; // 100MHz Clock
    localparam NUM_REGS = 4;
    localparam  DATA_WIDTH = 36;
    localparam ADDRESS_WIDTH = $clog2(NUM_REGS);
    

    // Inputs
    reg r_clk = 0;
    reg r_rst = 0; 
    reg [ADDRESS_WIDTH-1:0] r_rs1 = 0;
    reg [ADDRESS_WIDTH-1:0] r_rs2 = 0; 
    reg [ADDRESS_WIDTH-1:0] r_rd = 0;
    reg [DATA_WIDTH-1:0]    r_wdata = 0;
    reg r_wen = 0;

    // Outputs
    wire  [DATA_WIDTH-1:0] w_rs1_data;
    wire [DATA_WIDTH-1:0] w_rs2_data;

    reg_file dut(
        .i_clk(r_clk),
        .i_rst(r_rst),
        .i_rs1(r_rs1),
        .i_rs2(r_rs2),
        .i_rd(r_rd),
        .i_wdata(r_wdata),
        .i_wen(r_wen),
        .o_rs1_data(w_rs1_data),
        .o_rs2_data(w_rs2_data)
    );

    // Test Stimulus

    // 1. Reset the register file and check all registers are 0
    // 2.Write to a register (e.g., R2) and verify you can read it back
    // 3.Try writing when i_wen = 0 and verify it doesn't change the value
    // 4. Simultaneously test reading from both ports

    // Clock Generation 
    always
        #(c_CLOCK_PERIOD_NS/2) r_clk <= !r_clk;

    initial
    begin

      // Toggle the rst pin on start up to ensure register values are initialized to 0.
      @(posedge r_clk);
      r_rst <= 1;
      @(posedge r_clk);
      r_rst <= 0; 

      // Write a value of 0x11 to R0, R1, R2 R3
      @(posedge r_clk);
      r_wen <= 1; 
      r_rd <= 0; 
      r_rs1 <= 0;
      r_wdata <= 36'h11;

      @(posedge r_clk); 

      @(posedge r_clk); 
      r_rd <= 1; 
      r_rs1 <= 1;
      r_wdata <= 36'h22;

      @(posedge r_clk);
      r_rd <= 2;
      r_rs1 <= 2;
      r_wdata <= 36'h33;

      @(posedge r_clk);
      r_rd <= 3; 
      r_rs1 <= 3;
      r_wdata <= 36'h123456789;

      // Disable wen, R4 value should not change 
      @(posedge r_clk);
      r_wen <= 0; 
      r_rd <= 3;
      r_wdata <= 36'h555;

      // Wait a clock cycle
      @(posedge r_clk);

      // Toggle the rst pin again to reset all registers.
      @(posedge r_clk);
      r_rst <= 1;
      @(posedge r_clk);
      r_rst <= 0; 

      // Read all of the registers to check they are properly reset.
      @(posedge r_clk);
      r_rs1 <= 0;
      r_rs2 <= 0;
      @(posedge r_clk);
      r_rs1 <= 1;
      r_rs2 <= 1;
      @(posedge r_clk);
      r_rs1 <= 2;
      r_rs2 <= 2;
      @(posedge r_clk);
      r_rs1 <= 3;
      r_rs2 <= 3;
      @(posedge r_clk);
      $finish;
   end
  
  initial 
  begin
    // Required to dump signals to EPWave
    $dumpfile("dump.vcd");
    $dumpvars(0);
  end

endmodule

testbench/dump.vcd
$date
	Sat May 03 19:30:07 2025
$end
$version
	Icarus Verilog
$end
$timescale
	1ps
$end
$scope module reg_file_tb $end
$var wire 36 ! w_rs1_data [35:0] $end
$var wire 36 " w_rs2_data [35:0] $end
$var reg 1 # r_clk $end
$var reg 2 $ r_rd [1:0] $end
$var reg 2 % r_rs1 [1:0] $end
$var reg 2 & r_rs2 [1:0] $end
$var reg 1 ' r_rst $end
$var reg 36 ( r_wdata [35:0] $end
$var reg 1 ) r_wen $end
$scope module dut $end
$var wire 1 * i_clk $end
$var wire 2 + i_rd [1:0] $end
$var wire 2 , i_rs1 [1:0] $end
$var wire 2 - i_rs2 [1:0] $end
$var wire 1 . i_rst $end
$var wire 36 / i_wdata [35:0] $end
$var wire 1 0 i_wen $end
$var integer 32 1 i [31:0] $end
$var reg 36 2 o_rs1_data [35:0] $end
$var reg 36 3 o_rs2_data [35:0] $end
$upscope $end
$upscope $end
$enddefinitions $end
#0
$dumpvars
bx 3
bx 2
b0 1
x0
bx /
x.
bx -
bx ,
bx +
x*
x)
bx (
x'
bx &
bx %
bx $
x#
bx "
bx !
$end
#50000
1'
1.
1#
1*
#100000
0#
0*
#150000
b0 3
b0 "
b0 2
b0 !
0'
0.
b100 1
1#
1*
#200000
0#
0*
#250000
b10001 (
b10001 /
1)
10
1#
1*
#300000
0#
0*
#350000
b10001 3
b10001 "
b10001 2
b10001 !
1#
1*
#400000
0#
0*
#450000
b0 2
b0 !
b100010 (
b100010 /
b1 %
b1 ,
b1 $
b1 +
1#
1*
#500000
0#
0*
#550000
b110011 (
b110011 /
b10 %
b10 ,
b10 $
b10 +
1#
1*
#600000
0#
0*
#650000
b100100011010001010110011110001001 (
b100100011010001010110011110001001 /
b11 %
b11 ,
b11 $
b11 +
1#
1*
#700000
0#
0*
#750000
b100100011010001010110011110001001 2
b100100011010001010110011110001001 !
b10101010101 (
b10101010101 /
0)
00
1#
1*
#800000
0#
0*
#850000
1#
1*
#900000
0#
0*
#950000
1'
1.
1#
1*
#1000000
0#
0*
#1050000
b0 3
b0 "
b0 2
b0 !
0'
0.
b100 1
1#
1*
#1100000
0#
0*
#1150000
b0 %
b0 ,
1#
1*
#1200000
0#
0*
#1250000
b1 &
b1 -
b1 %
b1 ,
1#
1*
#1300000
0#
0*
#1350000
b10 &
b10 -
b10 %
b10 ,
1#
1*
#1400000
0#
0*
#1450000
b11 &
b11 -
b11 %
b11 ,
1#
1*
