src/inst_mem.v

// Date: May 2nd, 2025: 
// Author: Evan Wu 

/* Instruction Module */
// Stores and fetches the program 18-bit instructions to be executed by the microprocessor. 
// Implemented in Von Neumann architecture, 
// Instruction are addressed by the lower 13 bits of the address space.
// Instruction memory occupies addresses 0x0000 to 0x1FFF (13-bit address space). 
// Data memory occupies addresses 0x2000 to 0x3FFF (13-bit address space). 

// Future improvements: 

module inst_mem #(
    parameter INSTRUCTION_MEM_SIZE = 8192,
    parameter INSTRUCTION_WIDTH    = 18,
    parameter INSTRUCTION_ADDR_WIDTH = $clog2(INSTRUCTION_MEM_SIZE)
) (
    input i_clk,
    input [INSTRUCTION_ADDR_WIDTH-1:0] i_address,
    output reg [INSTRUCTION_WIDTH-1:0] instruction
);
    
    // Defines Instruction 8kb memory array 
    reg [INSTRUCTION_WIDTH-1:0] memory [0:INSTRUCTION_MEM_SIZE-1]; 

    // Fetches an instruction from memory every clock cycle
    always @(posedge i_clk) 
        begin
            instruction <= memory[i_address];
        end
endmodule

testbench/inst_mem_tb.v


`timescale 1ns/ 1ps
`include "../src/inst_mem.v"

module inst_mem_tb;

    // Parameters
    localparam INSTRUCTION_MEM_SIZE    = 8192;
    localparam INSTRUCTION_WIDTH       = 18;
    localparam INSTRUCTION_ADDR_WIDTH  = $clog2(INSTRUCTION_MEM_SIZE);
    parameter c_CLOCK_PERIOD_NS        = 100;

    // Inputs
    reg r_clk = 0;
    reg [INSTRUCTION_ADDR_WIDTH-1:0] i_address;

    // Output
    wire [INSTRUCTION_WIDTH-1:0] o_instruction;

    // Instantiate the Instruction Memory
    inst_mem #(
        .INSTRUCTION_MEM_SIZE(INSTRUCTION_MEM_SIZE),
        .INSTRUCTION_WIDTH(INSTRUCTION_WIDTH)
    ) uut (
        .i_clk(r_clk),
        .i_address(i_address),
        .instruction(o_instruction)
    );

    // Clock generation
    always
        #(c_CLOCK_PERIOD_NS/2) r_clk <= !r_clk;


    always @(posedge r_clk) begin
        $display("Time: %0t | Addr: %0d | Instruction: %0h", $time, i_address, o_instruction);
    end


    // Test data
    initial begin
        // Initialize signals
        r_clk = 0;
        i_address = 0;

        // Preload memory (optional: create `program.hex` file with 18-bit hex values)
        $readmemh("program.hex", uut.memory);

        // Wait and then test a few addresses
        i_address <= 0;
        @(posedge r_clk)
        i_address <= 1;
        @(posedge r_clk)
        i_address <= 2;
        @(posedge r_clk)
        i_address <= 3;
        @(posedge r_clk)
        i_address <= 4;
        @(posedge r_clk)
        i_address <= 5;
        @(posedge r_clk)
        i_address <= 100;
        @(posedge r_clk)
        i_address <= 8191; // Edge of memory
        @(posedge r_clk)
        $finish;
    end
    
    initial
    begin
        // Required to dump signals to EPWave
        $dumpfile("dump.vcd");
        $dumpvars(0);
    end
endmodule

testbench/dump.vcd
$date
	Fri May 02 17:04:11 2025
$end
$version
	Icarus Verilog
$end
$timescale
	1ps
$end
$scope module inst_mem_tb $end
$var wire 18 ! o_instruction [17:0] $end
$var reg 13 " i_address [12:0] $end
$var reg 1 # r_clk $end
$scope module uut $end
$var wire 13 $ i_address [12:0] $end
$var wire 1 % i_clk $end
$var reg 18 & instruction [17:0] $end
$upscope $end
$upscope $end
$enddefinitions $end
#0
$dumpvars
bx &
0%
b0 $
0#
b0 "
bx !
$end
#50000
b1 &
b1 !
b1 "
b1 $
1#
1%
#100000
0#
0%
#150000
b10 "
b10 $
b10010001101000101 &
b10010001101000101 !
1#
1%
#200000
0#
0%
#250000
b101010101010101010 &
b101010101010101010 !
b11 "
b11 $
1#
1%
#300000
0#
0%
#350000
b100 "
b100 $
b111111001111110011 &
b111111001111110011 !
1#
1%
#400000
0#
0%
#450000
b1100000011000000 &
b1100000011000000 !
b101 "
b101 $
1#
1%
#500000
0#
0%
#550000
b1100100 "
b1100100 $
b11101000111010001 &
b11101000111010001 !
1#
1%
#600000
0#
0%
#650000
bx &
bx !
b1111111111111 "
b1111111111111 $
1#
1%
